Metadata-Version: 2.1
Name: W-k-NN
Version: 0.0.3
Summary: A W-k-NN implementation with PyKeOps
Project-URL: Homepage, https://gitlab.inria.fr/cedubois/w-k-nn
Project-URL: Bug Tracker, https://gitlab.inria.fr/cedubois/w-k-nn/-/issues
Author-email: Cedric Dubois <cedric.dubois@inria.fr>
License-File: LICENCE.txt
Classifier: License :: OSI Approved :: MIT License
Classifier: Operating System :: OS Independent
Classifier: Programming Language :: Python :: 3
Requires-Python: >=3.7
